{"repo":"geoarrow/deck.gl-geoarrow","repo_stars":153,"repo_forks":12,"repo_createdAt":"2023-08-07T19:34:30Z","repo_updatedAt":"2026-04-16T01:12:28Z","repo_total_commits":116,"repo_url":"https://github.com/geoarrow/deck.gl-geoarrow","repo_description":"deck.gl layers for rendering GeoArrow data","repo_languages":"TypeScript,Python","repo_watchers":10,"repo_open_issues":32,"repo_license":"MIT","repo_topics":"apache-arrow,deck-gl,geoarrow,data-visualization,geospatial,map-visualization","repo_has_discussions":false,"repo_has_wiki":true,"repo_default_branch":"main","repo_archived":false,"repo_total_contributors":7,"repo_core_contributors":2,"repo_external_contributors":5,"repo_community_ratio":0.714}